docs_server/__init__.py
docs_server/__main__.py
docs_server/caching.py
docs_server/config.py
docs_server/helpers.py
docs_server/llms_service.py
docs_server/main.py
docs_server/markdown_service.py
docs_server/templates.py
docs_server/mcp/__init__.py
docs_server/mcp/cli.py
docs_server/mcp/indexer.py
docs_server/mcp/models.py
docs_server/mcp/schema.py
docs_server/mcp/search.py
docs_server/mcp/server.py
docs_server/mcp/tools.py
servemd-0.1.0.dist-info/METADATA
servemd-0.1.0.dist-info/WHEEL
servemd-0.1.0.dist-info/entry_points.txt
servemd-0.1.0.dist-info/licenses/LICENSE
servemd-0.1.0.dist-info/RECORD
