Metadata-Version: 2.4
Name: servemd
Version: 0.1.0
Summary: Beautiful markdown documentation server for humans and AI with native llms.txt support
Project-URL: Homepage, https://github.com/jberends/servemd
Project-URL: Documentation, https://github.com/jberends/servemd/blob/main/docs/index.md
Project-URL: Repository, https://github.com/jberends/servemd
Project-URL: Issues, https://github.com/jberends/servemd/issues
Project-URL: Changelog, https://github.com/jberends/servemd/blob/main/CHANGELOG.md
Author-email: Jochem Berends <jochem@gmail.nl>
License-Expression: Apache-2.0
License-File: LICENSE
Keywords: ai,docs,documentation,fastapi,llms,markdown,mcp,server
Classifier: Development Status :: 5 - Production/Stable
Classifier: Framework :: FastAPI
Classifier: Intended Audience :: Developers
Classifier: License :: OSI Approved :: Apache Software License
Classifier: Programming Language :: Python :: 3
Classifier: Programming Language :: Python :: 3.11
Classifier: Programming Language :: Python :: 3.12
Classifier: Programming Language :: Python :: 3.13
Classifier: Programming Language :: Python :: 3.14
Classifier: Topic :: Documentation
Classifier: Topic :: Internet :: WWW/HTTP :: HTTP Servers
Classifier: Topic :: Scientific/Engineering :: Artificial Intelligence
Classifier: Topic :: Software Development :: Documentation
Classifier: Topic :: Text Processing :: Markup :: Markdown
Requires-Python: >=3.11
Requires-Dist: fastapi>=0.128.0
Requires-Dist: jinja2>=3.1.6
Requires-Dist: markdown>=3.10.1
Requires-Dist: pygments>=2.19.2
Requires-Dist: pymdown-extensions>=10.20.1
Requires-Dist: python-multipart>=0.0.22
Requires-Dist: slowapi>=0.1.9
Requires-Dist: uvicorn[standard]>=0.40.0
Requires-Dist: whoosh>=2.7.4
